tf_kofn_robust_policy_optimization/__init__.py
tf_kofn_robust_policy_optimization/discounted_mdp.py
tf_kofn_robust_policy_optimization/pr_mdp.py
tf_kofn_robust_policy_optimization/regret_table.py
tf_kofn_robust_policy_optimization/environments/__init__.py
tf_kofn_robust_policy_optimization/environments/gridworld.py
tf_kofn_robust_policy_optimization/environments/inventory.py
tf_kofn_robust_policy_optimization/robust/__init__.py
tf_kofn_robust_policy_optimization/robust/kofn.py
tf_kofn_robust_policy_optimization/utils/__init__.py
tf_kofn_robust_policy_optimization/utils/probability.py
tf_kofn_robust_policy_optimization/utils/random.py
tf_kofn_robust_policy_optimization/utils/sampling.py
tf_kofn_robust_policy_optimization/utils/sequence.py
tf_kofn_robust_policy_optimization/utils/tensor.py
tf_kofn_robust_policy_optimization-1.0.3.dist-info/METADATA
tf_kofn_robust_policy_optimization-1.0.3.dist-info/RECORD
tf_kofn_robust_policy_optimization-1.0.3.dist-info/WHEEL
tf_kofn_robust_policy_optimization-1.0.3.dist-info/top_level.txt
