Metadata-Version: 2.1
Name: tf-kofn-robust-policy-optimization
Version: 1.0.3
Summary: UNKNOWN
Home-page: UNKNOWN
Author: UNKNOWN
Author-email: UNKNOWN
License: UNKNOWN
Platform: UNKNOWN
Requires-Dist: setuptools (>=20.2.2)
Requires-Dist: fire
Requires-Dist: numpy
Requires-Dist: scipy
